MANIFEST.in
README.rst
metadata.py
setup.py
celery_redis_unixsocket/__init__.py
celery_redis_unixsocket/broker.py
celery_redis_unixsocket/store.py
celery_redis_unixsocket.egg-info/PKG-INFO
celery_redis_unixsocket.egg-info/SOURCES.txt
celery_redis_unixsocket.egg-info/dependency_links.txt
celery_redis_unixsocket.egg-info/not-zip-safe
celery_redis_unixsocket.egg-info/requires.txt
celery_redis_unixsocket.egg-info/top_level.txt