Metadata-Version: 1.1
Name: celery-redis-unixsocket
Version: 0.3
Summary: celery store backend and kombu transport for redis that supports connections via unix sockets
Home-page: http://github.com/piquadrat/celery-redis-unixsocket
Author: Benjamin Wohlwend
Author-email: piquadrat@gmail.com
License: BSD
Platform: OS Independent
Classifier: Development Status :: 4 - Beta
Classifier: Framework :: Django
Classifier: Intended Audience :: Developers
Classifier: License :: OSI Approved :: BSD License
Classifier: Operating System :: OS Independent
Classifier: Programming Language :: Python
Classifier: Topic :: Internet :: WWW/HTTP
